tesseractpkg/__init__.py
tesseractpkg/structseq.h
tesseractpkg/sysmodule.h
tesseractpkg/token.h
tesseractpkg/traceback.h
tesseractpkg/tracemalloc.h
tesseractpkg/tupleobject.h
tesseractpkg/typeslots.h
tesseractpkg/unicodeobject.h
tesseractpkg/app/__init__.py
tesseractpkg/app/app.cpython-39-x86_64-linux-gnu.so
tesseractpkg/app/intrcheck.h
tesseractpkg/app/iterobject.h
tesseractpkg/app/listobject.h
tesseractpkg/app/logger.cpython-39-x86_64-linux-gnu.so
tesseractpkg/app/longintrepr.h
tesseractpkg/app/longobject.h
tesseractpkg/app/marshal.h
tesseractpkg/app/memoryobject.h
tesseractpkg/app/methodobject.h
tesseractpkg/app/modsupport.h
tesseractpkg/app/moduleobject.h
tesseractpkg/app/namespaceobject.h
tesseractpkg/app/object.h
tesseractpkg/app/objimpl.h
tesseractpkg/app/opcode.h
tesseractpkg/app/osdefs.h
tesseractpkg/app/osmodule.h
tesseractpkg/app/patchlevel.h
tesseractpkg/app/py_curses.h
tesseractpkg/app/pycapsule.h
tesseractpkg/app/pyconfig.h
tesseractpkg/app/pydtrace.h
tesseractpkg/app/pyerrors.h
tesseractpkg/app/pyexpat.h
tesseractpkg/app/pyframe.h
tesseractpkg/app/pyhash.h
tesseractpkg/app/pylifecycle.h
tesseractpkg/app/pymacconfig.h
tesseractpkg/app/pymanager.cpython-39-x86_64-linux-gnu.so
tesseractpkg/app/pyserver_ext.cpython-39-x86_64-linux-gnu.so
tesseractpkg/app/tesseract_ocr.cpython-39-x86_64-linux-gnu.so
tesseractpkg/app/utilts.cpython-39-x86_64-linux-gnu.so
tesseractpkg/data/__init__.py
tesseractpkg/data/data.pyd
tesseractpkg/log/__init__.py
tesseractpkg/log/log.pyd
tesseractpkg/model/__init__.py
tesseractpkg/model/model.pyd
tesseractpkg/utils/__init__.py
tesseractpkg/utils/utils.pyd
tesseractpkg-1.1.0.dist-info/METADATA
tesseractpkg-1.1.0.dist-info/WHEEL
tesseractpkg-1.1.0.dist-info/top_level.txt
tesseractpkg-1.1.0.dist-info/RECORD
