Metadata-Version: 2.4
Name: tesseractpkg
Version: 1.1.0
Summary: this is a program for EE
Author: 
Author-email: 
Requires-Dist: numpy==1.23.5
Requires-Dist: opencv-python-headless==4.5.4.60
Requires-Dist: Pillow==9.5.0
Requires-Dist: matplotlib==3.7.5
Requires-Dist: matplotlib-inline==0.1.6
Requires-Dist: requests==2.31.0
Requires-Dist: pyautogui==0.9.54
Requires-Dist: pyyaml==6.0.2
Requires-Dist: flask==3.1.1
Requires-Dist: gevent==25.5.1
Requires-Dist: pytesseract==0.3.13
Dynamic: requires-dist
Dynamic: summary
